mlops_mongodb_connect/__init__.py
mlops_mongodb_connect/mongo_crud.py
mlops_mongodb_connect-0.0.2.dist-info/METADATA
mlops_mongodb_connect-0.0.2.dist-info/WHEEL
mlops_mongodb_connect-0.0.2.dist-info/top_level.txt
mlops_mongodb_connect-0.0.2.dist-info/RECORD
