Metadata-Version: 2.1
Name: mlops_mongodb_connect
Version: 0.0.2
Summary: A python package for connecting with Mongo Database
Home-page: https://github.com/RockyLuvis/MLMongoConnect
Author: Raveendra Seetharam
Author-email: ravibhattinkw@gmail.com
License: MIT
Project-URL: Bug_Tracker, https://github.com/RockyLuvis/MLMongoConnect/issues
Classifier: Programming Language :: Python :: 3.7
Classifier: Programming Language :: Python :: 3.8
Classifier: Programming Language :: Python :: 3.9
Classifier: Operating System :: OS Independent
Requires-Python: >=3.7
Requires-Dist: scikit-learn
Requires-Dist: pandas
Requires-Dist: numpy
Requires-Dist: pytest
Requires-Dist: mypy
Provides-Extra: testing
Requires-Dist: pytest >=7.1.3 ; extra == 'testing'
Requires-Dist: mypy >=0.971 ; extra == 'testing'
Requires-Dist: flake8 >=5.0.4 ; extra == 'testing'
Requires-Dist: tox >=3.25.1 ; extra == 'testing'
Requires-Dist: black >=22.8.0 ; extra == 'testing'
